Workbook
Name \0: #REF!
Name \4: #REF!
Name \4AA: #REF!
Name \4AB: #REF!
Name \4CA: #REF!
Name \4CB: #REF!
Name \4D1A: #REF!
Name \4D1B: #REF!
Name \4D2A: #REF!
Name \4D2B: #REF!
Name \4E1A: #REF!
Name \4E1B: #REF!
Name \4E2A: #REF!
Name \4E2B: #REF!
Name \4GA: #REF!
Name \4GB: #REF!
Name \4HA: #REF!
Name \4HB: #REF!
Name \4LA: #REF!
Name \4LB: #REF!
Name \4TA: #REF!
Name \4TB: #REF!
Name \5BA: #REF!
Name \5BB: #REF!
Name \6BA: #REF!
Name \6BB: #REF!
Name \6CA: #REF!
Name \6CB: #REF!
Name \6LA: #REF!
Name \6LB: #REF!
Name \7AA: #REF!
Name \7AB: #REF!
Name \85A: #REF!
Name \85B: #REF!
Name \8BA: #REF!
Name \8BB: #REF!
Name \8FA: #REF!
Name \8FB: #REF!
Name \8TA: #REF!
Name \8TB: #REF!
Name \8VA: #REF!
Name \8VB: #REF!
Name \a: #REF!
Name \a_1: #N/A
Name \AA: #REF!
Name \b: #REF!
Name \B5: #REF!
Name \BS: #REF!
Name \c: #REF!
Name \d: #REF!
Name \E: #REF!
Name \f: #REF!
Name \g: #REF!
Name \h: #REF!
Name \i: #REF!
Name \j: #REF!
Name \k: #REF!
Name \l: #REF!
Name \m: #REF!
Name \n: #REF!

Sheet Note 6
A1: Dummy Entity | P1: ='[1]TB 31-03-24'!AL3 -> 100000
A2: Notes
A3: Amout in Lakhs
A5: 6 | B5: Property, Plant and Equipment and Capital work-in progress
C7: Gross block | D7: Gross Block | J7: Accumulated Depreciation | P7: Net block | R7: Net block
C8: Notes | D8: As at 1 April 2023 | E8: Acquisition through Business Combination Refer Note 34 | F8: Additions | G8: Deductions | H8: ="As at "&'[1]Statement of P&L'!E5 -> As at 31 March 2024 | J8: =D8 -> As at 1 April 2023 | K8: =E8 -> Acquisition through Business Combination Refer Note 34 | L8: For the year | M8: Deductions | N8: =H8 -> As at 31 March 2024 | P8: =N8 -> As at 31 March 2024 | Q8: =P27 -> As at 31 March 2023 | R8: As at 30 September 2023
B11: Owned assets | Z11: Property, Plant and Equipment
B12: Land | D12: =ROUND(H31,2) -> 476.17 | E12: 0 | F12: =ROUND(0,2) -> 0 | G12: =ROUND(0,2) -> 0 | H12: =SUM(D12:G12) -> 476.17 | J12: =ROUND(N31,2) -> 0 | K12: 0 | L12: =ROUND(0,2) -> 0 | M12: =ROUND(0,2) -> 0 | N12: =SUM(J12:M12) -> 0 | P12: =H12-N12 -> 476.17 | Q12: =P31 -> 476.17 | R12: 5405 | S12: =P12-R12 -> -4928.83 | AA12: =D12+F12-H12 -> 0
B13: Building-Factory | D13: =ROUND(H32,2) -> 482.03 | E13: 0 | F13: =ROUND(0,2) -> 0 | G13: =ROUND(0,2) -> 0 | H13: =SUM(D13:G13) -> 482.03 | J13: =ROUND(N32,2) -> 17.48 | K13: 0 | L13: =ROUND(16.07,2) -> 16.07 | M13: =ROUND(0,2) -> 0 | N13: =SUM(J13:M13) -> 33.55 | P13: =H13-N13 -> 448.48 | Q13: =P32 -> 464.55 | R13: 10854 | S13: =P13-R13 -> -10405.52 | AA13: =D13+F13-H13 -> 0
B14: Building-Others | D14: =ROUND(H33,2) -> 33.2 | E14: 0 | F14: =ROUND(0,2) -> 0 | G14: =ROUND(0,2) -> 0 | H14: =SUM(D14:G14) -> 33.2 | J14: =ROUND(N33,2) -> 12.04 | K14: 0 | L14: =ROUND(11.07,2) -> 11.07 | M14: =ROUND(0,2) -> 0 | N14: =SUM(J14:M14) -> 23.11 | P14: =H14-N14 -> 10.09 | Q14: =P33 -> 21.16 | R14: 282 | S14: =P14-R14 -> -271.91 | AA14: =D14+F14-H14 -> 0
B15: Plant and machinery | D15: =ROUND(H34,2) -> 3867.7 | E15: 0 | F15: =ROUND(7.25,2) -> 7.25 | G15: =ROUND(0,2) -> 0 | H15: =SUM(D15:G15) -> 3874.95 | J15: =ROUND(N34,2) -> 165.52 | K15: 0 | L15: =ROUND(154.77,2) -> 154.77 | M15: =ROUND(0,2) -> 0 | N15: =SUM(J15:M15) -> 320.29 | P15: =H15-N15 -> 3554.66 | Q15: =P34 -> 3702.18 | R15: 96645 | S15: =P15-R15 -> -93090.34 | AA15: =D15+F15-H15 -> 0
B16: Furniture and fixtures | D16: =ROUND(H35,2) -> 3.11 | E16: 0 | F16: =ROUND(0.2,2) -> 0.2 | G16: =ROUND(0,2) -> 0 | H16: =SUM(D16:G16) -> 3.31 | J16: =ROUND(N35,2) -> 0.39 | K16: 0 | L16: =ROUND(0.33,2) -> 0.33 | M16: =ROUND(0,2) -> 0 | N16: =SUM(J16:M16) -> 0.72 | P16: =H16-N16 -> 2.59 | Q16: =P35 -> 2.72 | R16: 11 | S16: =P16-R16 -> -8.41 | AA16: =D16+F16-H16 -> 0 | AC16: =L20+'[1]Note 7'!K12 -> 187.55
B17: Office Equipment | D17: =ROUND(H36,2) -> 21.21 | E17: 0 | F17: =ROUND(4.3,2) -> 4.3 | G17: =ROUND(0,2) -> 0 | H17: =SUM(D17:G17) -> 25.51 | J17: =ROUND(N36,2) -> 2.77 | K17: 0 | L17: =ROUND(4.39,2) -> 4.39 | M17: =ROUND(0,2) -> 0 | N17: =SUM(J17:M17) -> 7.16 | P17: =H17-N17 -> 18.35 | Q17: =P36 -> 18.44 | R17: 2 | S17: =P17-R17 -> 16.35 | AA17: =D17+F17-H17 -> 0
B18: Computers | D18: =ROUND(H37,2) -> 2.63 | E18: 0 | F18: =ROUND(0.63,2) -> 0.63 | G18: =ROUND(0,2) -> 0 | H18: =SUM(D18:G18) -> 3.26 | J18: =ROUND(N37,2) -> 0.98 | K18: 0 | L18: =ROUND(0.87,2) -> 0.87 | M18: =ROUND(0,2) -> 0 | N18: =SUM(J18:M18) -> 1.85 | P18: =H18-N18 -> 1.41 | Q18: =P37 -> 1.65 | R18: 152 | S18: =P18-R18 -> -150.59 | AA18: =D18+F18-H18 -> 0 | AC18: ='[1]TB 31-03-24'!$P$328 -> 0
B19: Vehicle | D19: =#REF! -> #REF! | E19: 0 | G19: 0 | K19: 0 | M19: 0 | N19: =SUM(J19:M19) -> 0 | P19: =H19-N19 -> 0 | Q19: =D19-J19 -> #REF! | R19: 2 | S19: =P19-R19 -> -2 | AA19: =D19+F19-H19 -> #REF!
B20: Total | D20: =SUM(D12:D18) -> 4886.05 | E20: =SUM(E12:E19) -> 0 | F20: =SUM(F12:F19) -> 12.38 | G20: =SUM(G12:G19) -> 0 | H20: =SUM(H12:H18) -> 4898.43 | J20: =SUM(J12:J19) -> 199.18 | K20: =SUM(K12:K19) -> 0 | L20: =SUM(L12:L19) -> 187.5 | M20: =SUM(M12:M19) -> 0 | N20: =SUM(N12:N19) -> 386.68 | P20: =SUM(P12:P19) -> 4511.75 | Q20: =SUM(Q12:Q18) -> 4686.87 | R20: =SUM(R12:R19) -> 113353 | S20: =SUM(S12:S19) -> -108841.25 | Z20: =SUM(P12:P19)-AG20 -> 4511.75 | AA20: =D20+F20-H20 -> 0 | AC20: Property, Plant and Equipment | AG20: =SUMIFS('[1]TB 31-03-24'!$R:$R,'[1]TB 31-03-24'!$L:$L,Z11) -> 0 | AH20: =P20-AG20 -> 4511.75
B23: Capital work-in progress | D23: =H41 -> 0 | E23: 0 | F23: =H23-D23 -> 0 | G23: 0 | H23: =+SUMIF('[1]TB 31-03-24'!M:M,'Note 6'!B41,'[1]TB 31-03-24'!R:R) -> 0 | J23: 0 | K23: 0 | L23: 0 | M23: 0 | N23: 0 | P23: =H23-N23 -> 0 | Q23: =P41 -> 0 | R23: 5242 | S23: =P23-R23 -> -5242 | Z23: =P23-SUM(D23:F23) -> 0 | AC23: Capital work-in-progress
R25: =P20-P12 -> 4035.58
C26: Gross block | D26: Gross Block | J26: =J7 -> Accumulated Depreciation | P26: Net block
C27: Notes | D27: As at 1 April 2022 | E27: Acquisition through Business Combination Refer Note 34 | F27: Additions | G27: Deductions | H27: As at 31 March 2023 | J27: =D27 -> As at 1 April 2022 | K27: =E27 -> Acquisition through Business Combination Refer Note 34 | L27: For the year | M27: Deductions | N27: =H27 -> As at 31 March 2023 | P27: =N27 -> As at 31 March 2023 | Q27: As at 1 April 2022
B30: Owned assets
A31: Land | B31: Land | D31: =ROUND(476.17,2) -> 476.17 | F31: =ROUND(0,2) -> 0 | G31: =ROUND(0,2) -> 0 | H31: =SUM(D31:G31) -> 476.17 | J31: =ROUND(0,2) -> 0 | K31: =ROUND(0,2) -> 0 | L31: =ROUND(0,2) -> 0 | M31: =ROUND(0,2) -> 0 | N31: =SUM(J31:M31) -> 0 | P31: =H31-N31 -> 476.17 | Q31: =D31-J31 -> 476.17 | Z31: =-SUMIFS('[1]FAR-April-Sept '!C:C,'[1]FAR-April-Sept '!A:A,'Note 6'!B31)/$P$1 -> 0 | AA31: =L31+Z31 -> 0
A32: Building-Factory | B32: Building-Factory | D32: =ROUND(482.03,2) -> 482.03 | F32: =ROUND(0,2) -> 0 | G32: =ROUND(0,2) -> 0 | H32: =SUM(D32:G32) -> 482.03 | J32: =ROUND(1.41,2) -> 1.41 | K32: 0 | L32: =ROUND(16.07,2) -> 16.07 | M32: =ROUND(0,2) -> 0 | N32: =SUM(J32:M32) -> 17.48 | P32: =H32-N32 -> 464.55 | Q32: =D32-J32 -> 480.62 | Z32: =-SUMIFS('[1]FAR-April-Sept '!C:C,'[1]FAR-April-Sept '!A:A,'Note 6'!B32)/$P$1 -> 196.59952 | AA32: =N32-Z32 -> -179.11952
A33: Building-Others | B33: Building-Others | D33: =ROUND(33.2,2) -> 33.2 | F33: =ROUND(0,2) -> 0 | G33: =ROUND(0,2) -> 0 | H33: =SUM(D33:G33) -> 33.2 | J33: =ROUND(0.97,2) -> 0.97 | K33: 0 | L33: =ROUND(11.07,2) -> 11.07 | M33: =ROUND(0,2) -> 0 | N33: =SUM(J33:M33) -> 12.04 | P33: =H33-N33 -> 21.16 | Q33: =D33-J33 -> 32.23 | Z33: =-SUMIFS('[1]FAR-April-Sept '!C:C,'[1]FAR-April-Sept '!A:A,'Note 6'!B33)/$P$1 -> 4.86302 | AA33: =N33-Z33 -> 7.17698
A34: Plant & Machinery | B34: Plant and machinery | D34: =ROUND(3731.36,2) -> 3731.36 | F34: =ROUND(136.34,2) -> 136.34 | G34: =ROUND(0,2) -> 0 | H34: =SUM(D34:G34) -> 3867.7 | J34: =ROUND(13.09,2) -> 13.09 | K34: 0 | L34: =ROUND(152.43,2) -> 152.43 | M34: =ROUND(0,2) -> 0 | N34: =SUM(J34:M34) -> 165.52 | P34: =H34-N34 -> 3702.18 | Q34: =D34-J34 -> 3718.27 | Z34: =-SUMIFS('[1]FAR-April-Sept '!C:C,'[1]FAR-April-Sept '!A:A,'Note 6'!B34)/$P$1 -> 1300.932 | AA34: =N34-Z34 -> -1135.412
A35: Furniture & Fixture | B35: Furniture and fixtures | D35: =ROUND(2.9,2) -> 2.9 | F35: =ROUND(0.21,2) -> 0.21 | G35: =ROUND(0,2) -> 0 | H35: =SUM(D35:G35) -> 3.11 | J35: =ROUND(0.1,2) -> 0.1 | K35: 0 | L35: =ROUND(0.29,2) -> 0.29 | M35: =ROUND(0,2) -> 0 | N35: =SUM(J35:M35) -> 0.39 | P35: =H35-N35 -> 2.72 | Q35: =D35-J35 -> 2.8 | Z35: =-SUMIFS('[1]FAR-April-Sept '!C:C,'[1]FAR-April-Sept '!A:A,'Note 6'!B35)/$P$1 -> 1.1819 | AA35: =N35-Z35 -> -0.7919
A36: Office Equipments | B36: Office Equipment | D36: =ROUND(2.97,2) -> 2.97 | F36: =ROUND(18.32,2) -> 18.32 | G36: =ROUND(-0.08,2) -> -0.08 | H36: =SUM(D36:G36) -> 21.21 | J36: =ROUND(0.23,2) -> 0.23 | K36: 0 | L36: =ROUND(2.54,2) -> 2.54 | M36: =ROUND(0,2) -> 0 | N36: =SUM(J36:M36) -> 2.77 | P36: =H36-N36 -> 18.44 | Q36: =D36-J36 -> 2.74 | Z36: =-SUMIFS('[1]FAR-April-Sept '!C:C,'[1]FAR-April-Sept '!A:A,'Note 6'!B36)/$P$1 -> 0.42508 | AA36: =N36-Z36 -> 2.34492
A37: Computors | B37: Computers | D37: =ROUND(1.32,2) -> 1.32 | F37: =ROUND(1.46,2) -> 1.46 | G37: =ROUND(-0.15,2) -> -0.15 | H37: =SUM(D37:G37) -> 2.63 | J37: =ROUND(0.26,2) -> 0.26 | K37: 0 | L37: =ROUND(0.72,2) -> 0.72 | M37: =ROUND(0,2) -> 0 | N37: =SUM(J37:M37) -> 0.98 | P37: =H37-N37 -> 1.65 | Q37: =D37-J37 -> 1.06 | Z37: =-SUMIFS('[1]FAR-April-Sept '!C:C,'[1]FAR-April-Sept '!A:A,'Note 6'!B37)/$P$1 -> 11.17771 | AA37: =N37-Z37 -> -10.19771
B38: Total | D38: =SUM(D31:D37) -> 4729.95 | E38: =SUM(E31:E37)+0.01 -> 0.01 | F38: =SUM(F31:F37) -> 156.33 | G38: =SUM(G31:G37) -> -0.23 | H38: =SUM(H31:H37) -> 4886.05 | J38: =SUM(J31:J37) -> 16.06 | K38: =SUM(K34:K37) -> 0 | L38: =SUM(L31:L37) -> 183.12 | M38: =SUM(M31:M37) -> 0 | N38: =SUM(N31:N37) -> 199.18 | P38: =SUM(P31:P37) -> 4686.87 | Q38: =SUM(Q31:Q37) -> 4713.89 | R38: =P38-'[1]Balance Sheet'!E8 -> -27.02 | Z38: =SUM(Z31:Z37) -> 1515.1792 | AA38: =SUM(AA31:AA37) -> -1315.9992
A41: Assets under constru | B41: Capital work-in progress | D41: 0 | E41: 26401.342 | F41: 0 | G41: 0 | H41: =+SUMIF('[1]TB 31-03-24'!M:M,'Note 6'!B41,'[1]TB 31-03-24'!Z:Z) -> 0 | J41: 0 | K41: 0 | L41: 0 | M41: 0 | N41: =SUM(J41:M41) -> 0 | P41: =H41-N41 -> 0 | Q41: =D41-J41 -> 0
C45: Gross block | D45: Gross Block | J45: Depreciation | P45: Net block
C46: Notes | D46: As at 1st April 2021 | E46: Acquisition through Business Combination Refer Note 34 | F46: Additions | G46: Deductions | H46: As at 31 March 2022 | J46: =D46 -> As at 1st April 2021 | K46: =E46 -> Acquisition through Business Combination Refer Note 34 | L46: For the year | M46: Deductions | N46: =H46 -> As at 31 March 2022 | P46: =N46 -> As at 31 March 2022 | Q46: =J46 -> As at 1st April 2021
B49: Owned assets | H49: =SUM(D49:G49) -> 0
B50: Land | D50: =ROUND(363.4617,2) -> 363.46 | F50: =ROUND(112.7105,2) -> 112.71 | G50: =ROUND(0,2) -> 0 | H50: =SUM(D50:G50) -> 476.17 | J50: =ROUND(0,2) -> 0 | L50: 0 | M50: =ROUND(0,2) -> 0 | N50: =SUM(J50:M50) -> 0 | P50: =H50-N50 -> 476.17 | Q50: 363.4617
B51: Building-Factory | D51: =ROUND(0,2) -> 0 | F51: =ROUND(482.0309,2) -> 482.03 | G51: =ROUND(0,2) -> 0 | H51: =SUM(D51:G51) -> 482.03 | J51: =ROUND(0,2) -> 0 | L51: =ROUND(1.4087,2) -> 1.41 | M51: =ROUND(0,2) -> 0 | N51: =SUM(J51:M51) -> 1.41 | P51: =H51-N51 -> 480.62 | Q51: 0
B52: Building-Others | D52: =ROUND(0,2) -> 0 | F52: =ROUND(33.1987,2) -> 33.2 | G52: =ROUND(0,2) -> 0 | H52: =SUM(D52:G52) -> 33.2 | J52: =ROUND(0,2) -> 0 | L52: =ROUND(0.9702,2) -> 0.97 | M52: =ROUND(0,2) -> 0 | N52: =SUM(J52:M52) -> 0.97 | P52: =H52-N52 -> 32.23 | Q52: 0
B53: Plant and machinery | D53: =ROUND(0,2) -> 0 | F53: =ROUND(3731.3529,2) -> 3731.35 | G53: =ROUND(0,2) -> 0 | H53: =SUM(D53:G53) -> 3731.35 | J53: =ROUND(0,2) -> 0 | L53: =ROUND(13.0853,2) -> 13.09 | M53: =ROUND(0,2) -> 0 | N53: =SUM(J53:M53) -> 13.09 | P53: =H53-N53 -> 3718.26 | Q53: 0
B54: Furniture and fixtures | D54: =ROUND(0,2) -> 0 | F54: =ROUND(2.8944,2) -> 2.89 | G54: =ROUND(0,2) -> 0 | H54: =SUM(D54:G54) -> 2.89 | J54: =ROUND(0,2) -> 0 | L54: =ROUND(0.0985,2) -> 0.1 | M54: =ROUND(0,2) -> 0 | N54: =SUM(J54:M54) -> 0.1 | P54: =H54-N54 -> 2.79 | Q54: 0
B55: Vehicles | D55: =ROUND(0.8354,2) -> 0.84 | F55: =ROUND(0,2) -> 0 | G55: =ROUND(0.8354,2) -> 0.84 | H55: =D55+F55-G55 -> 0 | J55: =ROUND(0.0032,) -> 0 | L55: =ROUND(0,2) -> 0 | M55: =ROUND(0.0032,2) -> 0 | N55: =SUM(J55:M55) -> 0 | P55: =H55-N55 -> 0
B56: Office Equipment | D56: =ROUND(0,2) -> 0 | F56: =ROUND(2.9716,2) -> 2.97 | G56: =ROUND(0,2) -> 0 | H56: =SUM(D56:G56) -> 2.97 | J56: =ROUND(0,2) -> 0 | L56: =ROUND(0.2289,2) -> 0.23 | M56: =ROUND(0,2) -> 0 | N56: =SUM(J56:M56) -> 0.23 | P56: =H56-N56 -> 2.74 | Q56: 0
B57: Computers | D57: =ROUND(0.424,2) -> 0.42 | F57: =ROUND(0.8863,2) -> 0.89 | G57: =ROUND(0,2) -> 0 | H57: =SUM(D57:G57) -> 1.31 | J57: =ROUND(0.0511,2) -> 0.05 | L57: =ROUND(0.2066,2) -> 0.21 | M57: =ROUND(0,2) -> 0 | N57: =SUM(J57:M57) -> 0.26 | P57: =H57-N57 -> 1.05 | Q57: 0.424
B58: Total | D58: =SUM(D50:D57) -> 364.72 | E58: =SUM(E50:E57)+0.01 -> 0.01 | F58: =SUM(F50:F57) -> 4366.04 | G58: =SUM(G50:G57) -> 0.84 | H58: =SUM(H50:H57) -> 4729.92 | J58: =SUM(J50:J57) -> 0.05 | L58: =SUM(L50:L57) -> 16.01 | M58: =SUM(M50:M57) -> 0 | N58: =SUM(N50:N57) -> 16.06 | P58: =SUM(P50:P57) -> 4713.86 | Q58: =SUM(Q50:Q57) -> 363.8857
B60: Capital work-in progress | D60: 0 | E60: 26401.342 | H60: =+SUMIF('[1]TB 31-03-24'!M:M,'Note 6'!B60,'[1]TB 31-03-24'!Z:Z) -> 0 | J60: 0 | K60: 0 | L60: 0 | M60: 0 | N60: =SUM(J60:M60) -> 0 | P60: =H60-N60 -> 0 | Q60: =D60-J60 -> 0
C61: Notes | D61: As at 1 April 2021 | E61: Acquisition through Business Combination | F61: Additions/ Adjustments | H61: As at 31 March 2022 | J61: =D61 -> As at 1 April 2021 | K61: Acquisition through Business Combination | L61: For the year | M61: Deductions/ Adjustments | N61: =H61 -> As at 31 March 2022 | P61: =N61 -> As at 31 March 2022 | Q61: As at 01 April 2021
B63: Owned assets
B64: Land | D64: 0 | E64: 0 | F64: 0 | H64: =SUM(D64:G64) -> 0 | J64: 0 | K64: 0 | L64: 0 | M64: 0 | N64: =SUM(J64:M64) -> 0 | P64: =H64-N64 -> 0 | Q64: =D64-J64 -> 0
B65: Buildings | D65: 0 | E65: 0 | F65: 0 | J65: 0 | K65: 0 | L65: 0 | M65: 0 | N65: =SUM(J65:M65) -> 0 | P65: =H65-N65 -> 0 | Q65: =D65-J65 -> 0
B66: Plant and Machinery | D66: 0 | E66: 0 | F66: 0 | H66: =SUM(D66:G66) -> 0 | J66: 0 | K66: 0 | L66: 0 | M66: 0 | N66: =SUM(J66:M66) -> 0 | P66: =H66-N66 -> 0 | Q66: =D66-J66 -> 0
B67: Furniture and Fixtures | D67: 0 | E67: 0 | F67: 0 | H67: =SUM(D67:G67) -> 0 | J67: 0 | K67: 0 | L67: 0 | M67: 0 | N67: =SUM(J67:M67) -> 0 | P67: =H67-N67 -> 0 | Q67: =D67-J67 -> 0
B68: Office Equipment | D68: 0 | E68: 0 | F68: 0 | H68: =SUM(D68:G68) -> 0 | J68: 0 | K68: 0 | L68: 0 | M68: 0 | N68: =SUM(J68:M68) -> 0 | P68: =H68-N68 -> 0 | Q68: =D68-J68 -> 0
B69: Computers | D69: 0 | E69: 0 | F69: 0 | H69: =SUM(D69:G69) -> 0 | J69: 0 | K69: 0 | L69: 0 | M69: 0 | N69: =SUM(J69:M69) -> 0 | P69: =H69-N69 -> 0 | Q69: =D69-J69 -> 0
B70: Vehicles | D70: 0 | E70: 0 | F70: 0 | H70: =SUM(D70:G70) -> 0 | J70: 0 | K70: 0 | L70: 0 | M70: 0 | N70: =SUM(J70:M70) -> 0 | P70: =H70-N70 -> 0 | Q70: =D70-J70 -> 0
B71: Total | D71: =SUM(D64:D70) -> 0 | E71: =SUM(E64:E70) -> 0 | F71: =SUM(F64:F70) -> 0 | H71: =SUM(H64:H70) -> 0 | J71: =SUM(J64:J70) -> 0 | K71: =SUM(K64:K70) -> 0 | L71: =SUM(L64:L70) -> 0 | M71: =SUM(M64:M70) -> 0 | N71: =SUM(N64:N70) -> 0 | P71: =SUM(P64:P70) -> 0 | Q71: =SUM(Q64:Q70) -> 0
B72: Capital work-in progress
A73: Assets under constru | B73: Capital work-in progress | D73: 0 | E73: 26401.342 | H73: =+SUMIF('[1]TB 31-03-24'!M:M,'Note 6'!B73,'[1]TB 31-03-24'!AD:AD) -> 0 | J73: 0 | K73: 0 | L73: 0 | M73: 0 | N73: =SUM(J73:M73) -> 0 | P73: =H73-N73 -> 0 | Q73: =D73-J73 -> 0
B75: Notes:
B76: a) The Company has availed loans from banks against security of the fixed assets (i.e. property, plant and equipment), refer note 52.
B77: b) The Company has not revalued its property, plant and equipment during the current year.
B78: c) For capital commitment with regards to property plant and equipment, refer note 54.
A79: 5.1 | B79: Property, plant and equipment pledged as security
B80: Refer Note 48 for information on property, plant and equipment pledged as security by the Company
AA81: -2.0703836e+08
A82: 5.1 | B82: Capital work-in progress (CWIP) | AA82: =N38+AA83 -> 199.64
AA83: ='[1]Note 7'!I12 -> 0.46
B84: Capital-work-in progress ageing schedule | AA84: =AA81+AA82 -> -2.0703816e+08
B86: As at 31 December 2023
B88: As at 31 March 2024
B89: Particulars | C89: Amount in CWIP for a period of | G89: Total
C90: Less than 1 year | D90: 1-2 years | E90: 2-3 years | F90: More than 3 years
B91: Projects in progress | C91: 96187640 | D91: =H23 -> 0 | E91: 0 | F91: 0 | G91: =SUM(D91:F91) -> 0
B92: Projects temporarily suspended | C92: 0 | D92: 0 | E92: 0 | F92: 0 | G92: 0
B94: As at 31 March 2023
B95: Particulars | C95: Amount in CWIP for a period of | G95: Total
C96: Less than 1 year | D96: 1-2 years | E96: 2-3 years | F96: More than 3 years
B97: Projects in progress | C97: 96187640 | D97: =H41 -> 0 | E97: 0 | F97: 0 | G97: =SUM(D97:F97) -> 0
B98: Projects temporarily suspended | C98: 0 | D98: 0 | E98: 0 | F98: 0 | G98: 0
B104: As at 1 April 2022
B105: Particulars | C105: Amount in CWIP for a period of | G105: Total
C106: Less than 1 year | D106: 1-2 years | E106: 2-3 years | F106: More than 3 years
B107: Projects in progress | C107: 96187640 | D107: =H73 -> 0 | E107: 0 | F107: 0 | G107: =SUM(D107:F107) -> 0
B108: Projects temporarily suspended | C108: 0 | D108: 0 | E108: 0 | F108: 0 | G108: 0
B110: There are no projects under Capital Work in progress where the completion is overdue or has exceeded its cost compared to its original plan.
K130: =-+SUMIF('[1]TB 31-03-24'!M:M,'[1]Notes 14 to 22'!B136,'[1]TB 31-03-24'!AD:AD) -> 2940
J168: =-+SUMIF('[1]TB 31-03-24'!M:M,C168,'[1]TB 31-03-24'!Z:Z) -> 0 | K168: =-+SUMIF('[1]TB 31-03-24'!M:M,C168,'[1]TB 31-03-24'!AD:AD) -> -0.01
I169: =-+SUMIF('[1]TB 31-03-24'!M:M,C169,'[1]TB 31-03-24'!R:R) -> 0 | J169: =-+SUMIF('[1]TB 31-03-24'!M:M,C169,'[1]TB 31-03-24'!Z:Z) -> 0 | K169: =-+SUMIF('[1]TB 31-03-24'!N:N,C169,'[1]TB 31-03-24'!AD:AD) -> 0
I171: =-+SUMIF('[1]TB 31-03-24'!M:M,A171,'[1]TB 31-03-24'!R:R) -> 0
B258: (p)
